vasperamemory/__init__.py
vasperamemory/client.py
vasperamemory/exceptions.py
vasperamemory/types.py
vasperamemory/integrations/__init__.py
vasperamemory/integrations/langchain.py
vasperamemory/integrations/llamaindex.py
vasperamemory-0.2.0.dist-info/METADATA
vasperamemory-0.2.0.dist-info/WHEEL
vasperamemory-0.2.0.dist-info/RECORD
