Metadata-Version: 2.4
Name: vasperamemory
Version: 0.2.0
Summary: Universal AI memory layer - Python SDK
Project-URL: Homepage, https://vasperamemory.com
Project-URL: Documentation, https://docs.vasperamemory.com
Project-URL: Repository, https://github.com/RCOLKITT/VasperaMemory
Project-URL: Issues, https://github.com/RCOLKITT/VasperaMemory/issues
Author-email: Vaspera Capital <support@vasperacapital.com>
License-Expression: MIT
Keywords: agents,ai,context,langchain,llamaindex,llm,memory,rag
Classifier: Development Status :: 4 - Beta
Classifier: Intended Audience :: Developers
Classifier: License :: OSI Approved :: MIT License
Classifier: Programming Language :: Python :: 3
Classifier: Programming Language :: Python :: 3.9
Classifier: Programming Language :: Python :: 3.10
Classifier: Programming Language :: Python :: 3.11
Classifier: Programming Language :: Python :: 3.12
Classifier: Topic :: Scientific/Engineering :: Artificial Intelligence
Requires-Python: >=3.9
Requires-Dist: httpx>=0.25.0
Requires-Dist: pydantic>=2.0.0
Provides-Extra: all
Requires-Dist: crewai>=0.1.0; extra == 'all'
Requires-Dist: langchain-core>=0.1.0; extra == 'all'
Requires-Dist: langchain>=0.1.0; extra == 'all'
Requires-Dist: llama-index>=0.10.0; extra == 'all'
Provides-Extra: crewai
Requires-Dist: crewai>=0.1.0; extra == 'crewai'
Provides-Extra: dev
Requires-Dist: mypy>=1.0.0; extra == 'dev'
Requires-Dist: pytest-asyncio>=0.21.0; extra == 'dev'
Requires-Dist: pytest-cov>=4.0.0; extra == 'dev'
Requires-Dist: pytest>=7.0.0; extra == 'dev'
Requires-Dist: ruff>=0.1.0; extra == 'dev'
Provides-Extra: langchain
Requires-Dist: langchain-core>=0.1.0; extra == 'langchain'
Requires-Dist: langchain>=0.1.0; extra == 'langchain'
Provides-Extra: llamaindex
Requires-Dist: llama-index>=0.10.0; extra == 'llamaindex'
